logging_emr/__init__.py
logging_emr/cloudwatch_logger.py
logging_emr/emr_utils.py
logging_emr-0.1.6.dist-info/licenses/LICENSE
logging_emr-0.1.6.dist-info/METADATA
logging_emr-0.1.6.dist-info/WHEEL
logging_emr-0.1.6.dist-info/top_level.txt
logging_emr-0.1.6.dist-info/RECORD
